Workbook

Sheet hdd_orders
Q1: CUSTOMER CHECK | U1: Price Match -- Sales Validation
A2: order_id | B2: product_id | C2: customer_id | D2: customer_segment | E2: quantity | F2: unit_price | G2: total_price | H2: discount_amount | I2: shipping_cost | J2: order_date | K2: shipping_date | L2: ship_to_city | M2: carrier | N2: order_status | O2: sales_channel | P2: payment_method | Q2: Customer_ID | R2: Customer_Segment | S2: Customer_ID Check | T2: Customer_Segment Check | U2: UNIT PRICE MATCH? | V2: unit price check | W2: P * Q | X2: P * Q Check | Y2: TRUE | Z2: all information imported is true
A3: 1 | B3: 1004 | C3: 51347 | D3: =_xlfn.XLOOKUP(C3,customer_table!$A$2:$A$4869,customer_table!$B$2:$B$4869) -> Consumer | E3: 2 | F3: 170.85 | G3: 341.7 | H3: 0 | I3: 8.05 | J3: 45409 | K3: 45416 | L3: Sacramento | M3: UPS | N3: Delivered | O3: Distributor | P3: Wire Transfer | Q3: =_xlfn.XLOOKUP(C3,customer_table!$A$2:$A$4947,customer_table!$A$2:$A$4947) -> 51347 | R3: =_xlfn.XLOOKUP(D3,customer_table!$B$2:$B$4947,customer_table!$B$2:$B$4947) -> Consumer | S3: =Q3=C3 -> TRUE | T3: =R3=D3 -> TRUE | U3: {=INDEX(hdd_products!$H$2:$H$21,MATCH(1,(hdd_products!$A$2:$A$21=hdd_orders!B3)*(hdd_products!$H$2:$H$21=hdd_orders!F3),0))} -> 170.85 | V3: =U3=F3 -> TRUE | W3: =F3*E3 -> 341.7 | X3: =G3=W3 -> TRUE
A4: 2 | B4: 1001 | C4: 95909 | D4: =_xlfn.XLOOKUP(C4,customer_table!$A$2:$A$4869,customer_table!$B$2:$B$4869) -> Consumer | E4: 2 | F4: 129.17 | G4: 258.34 | H4: 0 | I4: 9.93 | J4: 45582 | K4: 45588 | L4: Phoenix | M4: UPS | N4: Processing | O4: Online | P4: Wire Transfer | Q4: =_xlfn.XLOOKUP(C4,customer_table!$A$2:$A$4947,customer_table!$A$2:$A$4947) -> 95909 | R4: =_xlfn.XLOOKUP(D4,customer_table!$B$2:$B$4947,customer_table!$B$2:$B$4947) -> Consumer | S4: =Q4=C4 -> TRUE | T4: =R4=D4 -> TRUE | U4: {=INDEX(hdd_products!$H$2:$H$21,MATCH(1,(hdd_products!$A$2:$A$21=hdd_orders!B4)*(hdd_products!$H$2:$H$21=hdd_orders!F4),0))} -> 129.17 | V4: =U4=F4 -> TRUE | W4: =F4*E4 -> 258.34 | X4: =G4=W4 -> TRUE
A5: 3 | B5: 1010 | C5: 28301 | D5: =_xlfn.XLOOKUP(C5,customer_table!$A$2:$A$4869,customer_table!$B$2:$B$4869) -> Enterprise | E5: 1 | F5: 446.61 | G5: 446.61 | H5: 0 | I5: 13.42 | J5: 45621 | K5: 45625 | L5: Dallas | M5: UPS | N5: Delivered | O5: Online | P5: Debit Card | Q5: =_xlfn.XLOOKUP(C5,customer_table!$A$2:$A$4947,customer_table!$A$2:$A$4947) -> 28301 | R5: =_xlfn.XLOOKUP(D5,customer_table!$B$2:$B$4947,customer_table!$B$2:$B$4947) -> Enterprise | S5: =Q5=C5 -> TRUE | T5: =R5=D5 -> TRUE | U5: {=INDEX(hdd_products!$H$2:$H$21,MATCH(1,(hdd_products!$A$2:$A$21=hdd_orders!B5)*(hdd_products!$H$2:$H$21=hdd_orders!F5),0))} -> 446.61 | V5: =U5=F5 -> TRUE | W5: =F5*E5 -> 446.61 | X5: =G5=W5 -> TRUE
A6: 4 | B6: 1004 | C6: 86484 | D6: =_xlfn.XLOOKUP(C6,customer_table!$A$2:$A$4869,customer_table!$B$2:$B$4869) -> Enterprise | E6: 1 | F6: 170.85 | G6: 170.85 | H6: 0 | I6: 18.33 | J6: 45426 | K6: 45432 | L6: Boston | M6: UPS | N6: Delivered | O6: Online | P6: Wire Transfer | Q6: =_xlfn.XLOOKUP(C6,customer_table!$A$2:$A$4947,customer_table!$A$2:$A$4947) -> 86484 | R6: =_xlfn.XLOOKUP(D6,customer_table!$B$2:$B$4947,customer_table!$B$2:$B$4947) -> Enterprise | S6: =Q6=C6 -> TRUE | T6: =R6=D6 -> TRUE | U6: {=INDEX(hdd_products!$H$2:$H$21,MATCH(1,(hdd_products!$A$2:$A$21=hdd_orders!B6)*(hdd_products!$H$2:$H$21=hdd_orders!F6),0))} -> 170.85 | V6: =U6=F6 -> TRUE | W6: =F6*E6 -> 170.85 | X6: =G6=W6 -> TRUE
A7: 5 | B7: 1004 | C7: 16175 | D7: =_xlfn.XLOOKUP(C7,customer_table!$A$2:$A$4869,customer_table!$B$2:$B$4869) -> Small Business | E7: 2 | F7: 170.85 | G7: 341.7 | H7: 0 | I7: 13.47 | J7: 45362 | K7: 45367 | L7: Denver | M7: FedEx | N7: Delivered | O7: Online | P7: Credit Card | Q7: =_xlfn.XLOOKUP(C7,customer_table!$A$2:$A$4947,customer_table!$A$2:$A$4947) -> 16175 | R7: =_xlfn.XLOOKUP(D7,customer_table!$B$2:$B$4947,customer_table!$B$2:$B$4947) -> Small Business | S7: =Q7=C7 -> TRUE | T7: =R7=D7 -> TRUE | U7: {=INDEX(hdd_products!$H$2:$H$21,MATCH(1,(hdd_products!$A$2:$A$21=hdd_orders!B7)*(hdd_products!$H$2:$H$21=hdd_orders!F7),0))} -> 170.85 | V7: =U7=F7 -> TRUE | W7: =F7*E7 -> 341.7 | X7: =G7=W7 -> TRUE
A8: 6 | B8: 1006 | C8: 60432 | D8: =_xlfn.XLOOKUP(C8,customer_table!$A$2:$A$4869,customer_table!$B$2:$B$4869) -> Enterprise | E8: 5 | F8: 307.21 | G8: 1536.05 | H8: 0 | I8: 11.78 | J8: 45640 | K8: 45644 | L8: Seattle | M8: DHL | N8: Shipped | O8: Online | P8: Wire Transfer | Q8: =_xlfn.XLOOKUP(C8,customer_table!$A$2:$A$4947,customer_table!$A$2:$A$4947) -> 60432 | R8: =_xlfn.XLOOKUP(D8,customer_table!$B$2:$B$4947,customer_table!$B$2:$B$4947) -> Enterprise | S8: =Q8=C8 -> TRUE | T8: =R8=D8 -> TRUE | U8: {=INDEX(hdd_products!$H$2:$H$21,MATCH(1,(hdd_products!$A$2:$A$21=hdd_orders!B8)*(hdd_products!$H$2:$H$21=hdd_orders!F8),0))} -> 307.21 | V8: =U8=F8 -> TRUE | W8: =F8*E8 -> 1536.05 | X8: =G8=W8 -> TRUE
A9: 7 | B9: 1003 | C9: 11504 | D9: =_xlfn.XLOOKUP(C9,customer_table!$A$2:$A$4869,customer_table!$B$2:$B$4869) -> Enterprise | E9: 1 | F9: 95.08 | G9: 95.08 | H9: 0 | I9: 19.87 | J9: 45562 | K9: 45565 | L9: Miami | M9: UPS | N9: Delivered | O9: Distributor | P9: ACH | Q9: =_xlfn.XLOOKUP(C9,customer_table!$A$2:$A$4947,customer_table!$A$2:$A$4947) -> 11504 | R9: =_xlfn.XLOOKUP(D9,customer_table!$B$2:$B$4947,customer_table!$B$2:$B$4947) -> Enterprise | S9: =Q9=C9 -> TRUE | T9: =R9=D9 -> TRUE | U9: {=INDEX(hdd_products!$H$2:$H$21,MATCH(1,(hdd_products!$A$2:$A$21=hdd_orders!B9)*(hdd_products!$H$2:$H$21=hdd_orders!F9),0))} -> 95.08 | V9: =U9=F9 -> TRUE | W9: =F9*E9 -> 95.08 | X9: =G9=W9 -> TRUE
A10: 8 | B10: 1001 | C10: 94012 | D10: =_xlfn.XLOOKUP(C10,customer_table!$A$2:$A$4869,customer_table!$B$2:$B$4869) -> Consumer | E10: 2 | F10: 129.17 | G10: 258.34 | H10: 0 | I10: 17.06 | J10: 45566 | K10: 45573 | L10: Boston | M10: UPS | N10: Delivered | O10: Online | P10: PayPal | Q10: =_xlfn.XLOOKUP(C10,customer_table!$A$2:$A$4947,customer_table!$A$2:$A$4947) -> 94012 | R10: =_xlfn.XLOOKUP(D10,customer_table!$B$2:$B$4947,customer_table!$B$2:$B$4947) -> Consumer | S10: =Q10=C10 -> TRUE | T10: =R10=D10 -> TRUE | U10: {=INDEX(hdd_products!$H$2:$H$21,MATCH(1,(hdd_products!$A$2:$A$21=hdd_orders!B10)*(hdd_products!$H$2:$H$21=hdd_orders!F10),0))} -> 129.17 | V10: =U10=F10 -> TRUE | W10: =F10*E10 -> 258.34 | X10: =G10=W10 -> TRUE
A11: 9 | B11: 1005 | C11: 44522 | D11: =_xlfn.XLOOKUP(C11,customer_table!$A$2:$A$4869,customer_table!$B$2:$B$4869) -> Enterprise | E11: 2 | F11: 204.55 | G11: 409.1 | H11: 0 | I11: 7 | J11: 45372 | K11: 45376 | L11: Los Angeles | M11: DHL | N11: Shipped | O11: Retail | P11: Apple Pay | Q11: =_xlfn.XLOOKUP(C11,customer_table!$A$2:$A$4947,customer_table!$A$2:$A$4947) -> 44522 | R11: =_xlfn.XLOOKUP(D11,customer_table!$B$2:$B$4947,customer_table!$B$2:$B$4947) -> Enterprise | S11: =Q11=C11 -> TRUE | T11: =R11=D11 -> TRUE | U11: {=INDEX(hdd_products!$H$2:$H$21,MATCH(1,(hdd_products!$A$2:$A$21=hdd_orders!B11)*(hdd_products!$H$2:$H$21=hdd_orders!F11),0))} -> 204.55 | V11: =U11=F11 -> TRUE | W11: =F11*E11 -> 409.1 | X11: =G11=W11 -> TRUE
A12: 10 | B12: 1006 | C12: 93748 | D12: =_xlfn.XLOOKUP(C12,customer_table!$A$2:$A$4869,customer_table!$B$2:$B$4869) -> Consumer | E12: 1 | F12: 307.21 | G12: 307.21 | H12: 0 | I12: 9.24 | J12: 45346 | K12: 45353 | L12: Sacramento | M12: UPS | N12: Delivered | O12: Online | P12: Apple Pay | Q12: =_xlfn.XLOOKUP(C12,customer_table!$A$2:$A$4947,customer_table!$A$2:$A$4947) -> 93748 | R12: =_xlfn.XLOOKUP(D12,customer_table!$B$2:$B$4947,customer_table!$B$2:$B$4947) -> Consumer | S12: =Q12=C12 -> TRUE | T12: =R12=D12 -> TRUE | U12: {=INDEX(hdd_products!$H$2:$H$21,MATCH(1,(hdd_products!$A$2:$A$21=hdd_orders!B12)*(hdd_products!$H$2:$H$21=hdd_orders!F12),0))} -> 307.21 | V12: =U12=F12 -> TRUE | W12: =F12*E12 -> 307.21 | X12: =G12=W12 -> TRUE
A13: 11 | B13: 1004 | C13: 79514 | D13: =_xlfn.XLOOKUP(C13,customer_table!$A$2:$A$4869,customer_table!$B$2:$B$4869) -> Enterprise | E13: 1 | F13: 170.85 | G13: 170.85 | H13: 0 | I13: 16.64 | J13: 45483 | K13: 45490 | L13: Miami | M13: UPS | N13: Delivered | O13: Distributor | P13: Credit Card | Q13: =_xlfn.XLOOKUP(C13,customer_table!$A$2:$A$4947,customer_table!$A$2:$A$4947) -> 79514 | R13: =_xlfn.XLOOKUP(D13,customer_table!$B$2:$B$4947,customer_table!$B$2:$B$4947) -> Enterprise | S13: =Q13=C13 -> TRUE | T13: =R13=D13 -> TRUE | U13: {=INDEX(hdd_products!$H$2:$H$21,MATCH(1,(hdd_products!$A$2:$A$21=hdd_orders!B13)*(hdd_products!$H$2:$H$21=hdd_orders!F13),0))} -> 170.85 | V13: =U13=F13 -> TRUE | W13: =F13*E13 -> 170.85 | X13: =G13=W13 -> TRUE
A14: 12 | B14: 1002 | C14: 50306 | D14: =_xlfn.XLOOKUP(C14,customer_table!$A$2:$A$4869,customer_table!$B$2:$B$4869) -> Consumer | E14: 10 | F14: 198.26 | G14: 1982.6 | H14: 0 | I14: 19.71 | J14: 45301 | K14: 45302 | L14: Miami | M14: USPS | N14: Delivered | O14: Online | P14: Debit Card | Q14: =_xlfn.XLOOKUP(C14,customer_table!$A$2:$A$4947,customer_table!$A$2:$A$4947) -> 50306 | R14: =_xlfn.XLOOKUP(D14,customer_table!$B$2:$B$4947,customer_table!$B$2:$B$4947) -> Consumer | S14: =Q14=C14 -> TRUE | T14: =R14=D14 -> TRUE | U14: {=INDEX(hdd_products!$H$2:$H$21,MATCH(1,(hdd_products!$A$2:$A$21=hdd_orders!B14)*(hdd_products!$H$2:$H$21=hdd_orders!F14),0))} -> 198.26 | V14: =U14=F14 -> TRUE | W14: =F14*E14 -> 1982.6 | X14: =G14=W14 -> TRUE
... A5002: 5000 | B5002: 1003 | C5002: 74107 | D5002: =_xlfn.XLOOKUP(C5002,customer_table!$A$2:$A$4869,customer_table!$B$2:$B$4869) -> Enterprise | E5002: 1 | F5002: 95.08 | G5002: 95.08 | H5002: 0 | I5002: 18.88 | J5002: 45293 | K5002: 45294 | L5002: Boston | M5002: FedEx | N5002: Delivered | O5002: Distributor | P5002: PayPal | Q5002: =_xlfn.XLOOKUP(C5002,customer_table!$A$2:$A$4947,customer_table!$A$2:$A$4947) -> 74107 | R5002: =_xlfn.XLOOKUP(D5002,customer_table!$B$2:$B$4947,customer_table!$B$2:$B$4947) -> Enterprise | S5002: =Q5002=C5002 -> TRUE | T5002: =R5002=D5002 -> TRUE | U5002: {=INDEX(hdd_products!$H$2:$H$21,MATCH(1,(hdd_products!$A$2:$A$21=hdd_orders!B5002)*(hdd_products!$H$2:$H$21=hdd_orders!F5002),0))} -> 95.08 | V5002: =U5002=F5002 -> TRUE | W5002: =F5002*E5002 -> 95.08 | X5002: =G5002=W5002 -> TRUE
Y5004: Row Count | Z5004: =COUNT($A$3:$A$5002) -> 5000
Y5005: Row Count (mySQL) | Z5005: 5000
Y5006: Difference | Z5006: =Z5004-Z5005 -> 0 | AA5006: TRUE | AB5006: no variances in row count

Sheet customer_table
A1: customer_id | B1: customer_segment | C1: customer_street_address | D1: How Many Times Customer Purchases
A2: 10007 | B2: Enterprise | C2: 239 Oak Ave, Miami, NY 94462 | D2: =COUNTIF(hdd_orders!$C$3:$C$5002,customer_table!A2) -> 1
A3: 10046 | B3: Enterprise | C3: 5890 Pine Rd, Seattle, WA 98883 | D3: =COUNTIF(hdd_orders!$C$3:$C$5002,customer_table!A3) -> 1 | F3: Row Labels | G3: Count of customer_id
A4: 10055 | B4: Small Business | C4: 9616 Maple Dr, Chicago, CO 92020 | D4: =COUNTIF(hdd_orders!$C$3:$C$5002,customer_table!A4) -> 1 | F4: 1 | G4: 4738
A5: 10064 | B5: Enterprise | C5: 847 Pine Rd, Phoenix, CO 92567 | D5: =COUNTIF(hdd_orders!$C$3:$C$5002,customer_table!A5) -> 1 | F5: 2 | G5: 128
A6: 10100 | B6: Enterprise | C6: 5348 Oak Ave, Seattle, NY 95515 | D6: =COUNTIF(hdd_orders!$C$3:$C$5002,customer_table!A6) -> 1 | F6: 3 | G6: 2
A7: 10128 | B7: Enterprise | C7: 6024 Cedar Ln, Sacramento, IL 90196 | D7: =COUNTIF(hdd_orders!$C$3:$C$5002,customer_table!A7) -> 1 | F7: Grand Total | G7: 4868
A8: 10168 | B8: Small Business | C8: 2113 Pine Rd, Los Angeles, IL 93735 | D8: =COUNTIF(hdd_orders!$C$3:$C$5002,customer_table!A8) -> 1
A9: 10186 | B9: Small Business | C9: 9138 Main St, Boston, CO 91575 | D9: =COUNTIF(hdd_orders!$C$3:$C$5002,customer_table!A9) -> 1
A10: 10191 | B10: Small Business | C10: 7728 Cedar Ln, Chicago, IL 93170 | D10: =COUNTIF(hdd_orders!$C$3:$C$5002,customer_table!A10) -> 1
A11: 10193 | B11: Enterprise | C11: 1597 Maple Dr, Sacramento, WA 92960 | D11: =COUNTIF(hdd_orders!$C$3:$C$5002,customer_table!A11) -> 1
A12: 10206 | B12: Enterprise | C12: 4084 Maple Dr, Denver, WA 91123 | D12: =COUNTIF(hdd_orders!$C$3:$C$5002,customer_table!A12) -> 1
A13: 10208 | B13: Enterprise | C13: 4917 Oak Ave, Portland, CO 91243 | D13: =COUNTIF(hdd_orders!$C$3:$C$5002,customer_table!A13) -> 1
A14: 10302 | B14: Consumer | C14: 7402 Elm St, Chicago, CA 90901 | D14: =COUNTIF(hdd_orders!$C$3:$C$5002,customer_table!A14) -> 1
A15: 10336 | B15: Enterprise | C15: 9958 Cedar Ln, Chicago, NY 95479 | D15: =COUNTIF(hdd_orders!$C$3:$C$5002,customer_table!A15) -> 1
A16: 10350 | B16: Enterprise | C16: 4547 Oak Ave, Boston, NY 97002 | D16: =COUNTIF(hdd_orders!$C$3:$C$5002,customer_table!A16) -> 1
A17: 10365 | B17: Enterprise | C17: 4829 Elm St, Miami, WA 93818 | D17: =COUNTIF(hdd_orders!$C$3:$C$5002,customer_table!A17) -> 1
A18: 10373 | B18: Enterprise | C18: 510 Oak Ave, Los Angeles, MA 92746 | D18: =COUNTIF(hdd_orders!$C$3:$C$5002,customer_table!A18) -> 1
A19: 10391 | B19: Enterprise | C19: 5183 Pine Rd, Los Angeles, IL 95631 | D19: =COUNTIF(hdd_orders!$C$3:$C$5002,customer_table!A19) -> 1
... A4869: 99983 | B4869: Enterprise | C4869: 1626 Maple Dr, Boston, WA 98598 | D4869: =COUNTIF(hdd_orders!$C$3:$C$5002,customer_table!A4869) -> 1
C4872: Row Count | D4872: =COUNT(A2:A4869) -> 4868
C4873: Row Count (mySQL) | D4873: 4868
C4874: Difference | D4874: =D4872-D4873 -> 0 | E4874: TRUE | F4874: no variances in row count
B4949: Row Count | C4949: =COUNT($A$2:$A$4947) -> 4868
B4950: Rount Count (mySQL) | C4950: 4946
B4951: Difference | C4951: =C4949-C4950 -> -78 | D4951: TRUE | E4951: no variances in row count

Sheet hdd_products
A1: product_id | B1: product_name | C1: product_category | D1: manufacturing_city | E1: size | F1: color | G1: SKU | H1: unit_price | I1: Appears in Orders Table
A2: 1001 | B2: Internal HDD 2TB | C2: Internal HDD | D2: San Jose | E2: 2TB | F2: Blue | G2: 500001 | H2: 129.17 | I2: =_xlfn.XLOOKUP(A2,hdd_orders!$B$3:$B$5002,hdd_orders!$B$3:$B$5002,"Not Ordered") -> 1001
A3: 1002 | B3: Internal HDD 4TB | C3: Internal HDD | D3: Penang | E3: 4TB | F3: Black | G3: 500002 | H3: 198.26 | I3: =_xlfn.XLOOKUP(A3,hdd_orders!$B$3:$B$5002,hdd_orders!$B$3:$B$5002,"Not Ordered") -> 1002
A4: 1003 | B4: Internal HDD 20TB | C4: Internal HDD | D4: San Jose | E4: 20TB | F4: Red | G4: 500003 | H4: 95.08 | I4: =_xlfn.XLOOKUP(A4,hdd_orders!$B$3:$B$5002,hdd_orders!$B$3:$B$5002,"Not Ordered") -> 1003
A5: 1004 | B5: Internal HDD 2TB | C5: Internal HDD | D5: Austin | E5: 2TB | F5: Silver | G5: 500004 | H5: 170.85 | I5: =_xlfn.XLOOKUP(A5,hdd_orders!$B$3:$B$5002,hdd_orders!$B$3:$B$5002,"Not Ordered") -> 1004
A6: 1005 | B6: Internal HDD 1TB | C6: Internal HDD | D6: Bangkok | E6: 1TB | F6: Silver | G6: 500005 | H6: 204.55 | I6: =_xlfn.XLOOKUP(A6,hdd_orders!$B$3:$B$5002,hdd_orders!$B$3:$B$5002,"Not Ordered") -> 1005
A7: 1006 | B7: NAS HDD 20TB | C7: NAS HDD | D7: Taipei | E7: 20TB | F7: Silver | G7: 500006 | H7: 307.21 | I7: =_xlfn.XLOOKUP(A7,hdd_orders!$B$3:$B$5002,hdd_orders!$B$3:$B$5002,"Not Ordered") -> 1006
A8: 1007 | B8: NAS HDD 8TB | C8: NAS HDD | D8: Shenzhen | E8: 8TB | F8: Black | G8: 500007 | H8: 415.57 | I8: =_xlfn.XLOOKUP(A8,hdd_orders!$B$3:$B$5002,hdd_orders!$B$3:$B$5002,"Not Ordered") -> 1007
A9: 1008 | B9: NAS HDD 4TB | C9: NAS HDD | D9: Penang | E9: 4TB | F9: Red | G9: 500008 | H9: 269.08 | I9: =_xlfn.XLOOKUP(A9,hdd_orders!$B$3:$B$5002,hdd_orders!$B$3:$B$5002,"Not Ordered") -> 1008
A10: 1009 | B10: NAS HDD 4TB | C10: NAS HDD | D10: Austin | E10: 4TB | F10: Blue | G10: 500009 | H10: 185.76 | I10: =_xlfn.XLOOKUP(A10,hdd_orders!$B$3:$B$5002,hdd_orders!$B$3:$B$5002,"Not Ordered") -> 1009
A11: 1010 | B11: NAS HDD 12TB | C11: NAS HDD | D11: San Jose | E11: 12TB | F11: Blue | G11: 500010 | H11: 446.61 | I11: =_xlfn.XLOOKUP(A11,hdd_orders!$B$3:$B$5002,hdd_orders!$B$3:$B$5002,"Not Ordered") -> 1010
A12: 1011 | B12: Enterprise HDD 8TB | C12: Enterprise HDD | D12: Shenzhen | E12: 8TB | F12: Black | G12: 500011 | H12: 664.86 | I12: =_xlfn.XLOOKUP(A12,hdd_orders!$B$3:$B$5002,hdd_orders!$B$3:$B$5002,"Not Ordered") -> 1011
A13: 1012 | B13: Enterprise HDD 20TB | C13: Enterprise HDD | D13: San Jose | E13: 20TB | F13: Red | G13: 500012 | H13: 339.39 | I13: =_xlfn.XLOOKUP(A13,hdd_orders!$B$3:$B$5002,hdd_orders!$B$3:$B$5002,"Not Ordered") -> 1012
... A21: 1020 | B21: Portable HDD 12TB | C21: Portable HDD | D21: Singapore | E21: 12TB | F21: Silver | G21: 500020 | H21: 151.61 | I21: =_xlfn.XLOOKUP(A21,hdd_orders!$B$3:$B$5002,hdd_orders!$B$3:$B$5002,"Not Ordered") -> Not Ordered
G23: Row Count | H23: =COUNT($A$2:$A$21) -> 20
G24: Row Count (mySQL) | H24: 20
G25: Difference | H25: =H23-H24 -> 0 | I25: TRUE | J25: no variances in row count
